README
setup.py
EximSesTransport.egg-info/PKG-INFO
EximSesTransport.egg-info/SOURCES.txt
EximSesTransport.egg-info/dependency_links.txt
EximSesTransport.egg-info/entry_points.txt
EximSesTransport.egg-info/requires.txt
EximSesTransport.egg-info/top_level.txt
exim_ses_transport/__init__.py
exim_ses_transport/policy.py
exim_ses_transport/run.py
exim_ses_transport/transport.py