Metadata-Version: 1.1
Name: EximSesTransport
Version: 0.4
Summary: An Amazon SES transport for the Exim MTA.
Home-page: https://github.com/jvantuyl/exim_ses_transport
Author: Jayson Vantuyl
Author-email: jvantuyl@gmail.com
License: http://www.gnu.org/copyleft/lesser.html
Platform: any
Classifier: Topic :: Communications :: Email :: Filters
Classifier: License :: OSI Approved :: GNU Library or Lesser General Public License (LGPL)
